Metadata-Version: 1.0
Name: test-library
Version: 0.0.1
Summary: just a test
Home-page: UNKNOWN
Author: wujiating
Author-email: wujiating@mesalab.cn
License: UNKNOWN
Keywords: just a test
Platform: any
